servic_request_helper/__init__.py
servic_request_helper/abstracts.py
servic_request_helper/auth.py
servic_request_helper/errors.py
servic_request_helper/http_methods.py
servic_request_helper/request_formatters.py
servic_request_helper/types.py
servic_request_helper/utils.py
servic_request_helper/asyncs/__init__.py
servic_request_helper/asyncs/auth.py
servic_request_helper/asyncs/clients.py
servic_request_helper/asyncs/error_builders.py
servic_request_helper/asyncs/response_formatters.py
servic_request_helper/syncs/__init__.py
servic_request_helper/syncs/auth.py
servic_request_helper/syncs/clients.py
servic_request_helper/syncs/error_builders.py
servic_request_helper/syncs/response_formatters.py
test/__init__.py
test/test_async_auth.py
test/test_async_clien.py
test/test_async_response_formatters.py
test/test_async_with_server.py
test/test_request_formatters.py
test/test_sync_auth.py
test/test_sync_clien.py
test/test_sync_response_formatters.py
test/test_sync_with_server.py
service_request_helper-1.0.0.dist-info/METADATA
service_request_helper-1.0.0.dist-info/WHEEL
service_request_helper-1.0.0.dist-info/top_level.txt
service_request_helper-1.0.0.dist-info/RECORD
