Metadata-Version: 2.1
Name: service-request-helper
Version: 1.0.0
Summary: Helper for client request to rest api
Home-page: https://github.com/endpointuz/service-request-helper-lib
Author: ksinn
Author-email: ksinnd@gmail.com
Requires-Dist: pyhumps
Provides-Extra: async
Requires-Dist: aiohttp ; extra == 'async'
Provides-Extra: sync
Requires-Dist: requests ; extra == 'sync'
